avocet/__init__.py
avocet/avocet.py
avocet-1.0.2.dist-info/LICENSE
avocet-1.0.2.dist-info/METADATA
avocet-1.0.2.dist-info/WHEEL
avocet-1.0.2.dist-info/top_level.txt
avocet-1.0.2.dist-info/RECORD
