Metadata-Version: 2.1
Name: avocet
Version: 1.0.2
Summary: An easy to use Python package for encryption and decryption needs
Home-page: https://github.com/sidkris/avocet
Author: Siddharth Krishnan
Author-email: sid@sidkrishnan.com
License: MIT
Classifier: Programming Language :: Python :: 3
Classifier: License :: OSI Approved :: MIT License
Classifier: Operating System :: OS Independent
Requires-Python: >=3.6
License-File: LICENSE
Requires-Dist: pycryptodomex
